Nullberry0/__init__.py
Nullberry0/code.py
nullberry0-0.1.0.dist-info/METADATA
nullberry0-0.1.0.dist-info/WHEEL
nullberry0-0.1.0.dist-info/top_level.txt
nullberry0-0.1.0.dist-info/RECORD
