Metadata-Version: 2.4
Name: nullberry0
Version: 0.1.0
Summary: The official Nullberry0 extension
Author-email: Nullberry <example@gmail.com>
Requires-Python: >=3.8
